shapeandshare/darkness/__init__.py
shapeandshare/darkness/client/__init__.py
shapeandshare/darkness/client/state.py
shapeandshare/darkness/client/commands/__init__.py
shapeandshare/darkness/client/commands/abstract.py
shapeandshare/darkness/client/commands/chunk/__init__.py
shapeandshare/darkness/client/commands/chunk/create.py
shapeandshare/darkness/client/commands/chunk/delete.py
shapeandshare/darkness/client/commands/chunk/get.py
shapeandshare/darkness/client/commands/chunk/patch.py
shapeandshare/darkness/client/commands/chunk/quantum.py
shapeandshare/darkness/client/commands/entity/__init__.py
shapeandshare/darkness/client/commands/entity/delete.py
shapeandshare/darkness/client/commands/entity/get.py
shapeandshare/darkness/client/commands/entity/patch.py
shapeandshare/darkness/client/commands/metrics/__init__.py
shapeandshare/darkness/client/commands/metrics/health/__init__.py
shapeandshare/darkness/client/commands/metrics/health/get.py
shapeandshare/darkness/client/commands/tile/__init__.py
shapeandshare/darkness/client/commands/tile/delete.py
shapeandshare/darkness/client/commands/tile/get.py
shapeandshare/darkness/client/commands/tile/patch.py
shapeandshare/darkness/client/commands/world/__init__.py
shapeandshare/darkness/client/commands/world/create.py
shapeandshare/darkness/client/commands/world/delete.py
shapeandshare/darkness/client/commands/world/get.py
shapeandshare/darkness/client/commands/world/patch.py
shapeandshare/darkness/client/commands/worlds/__init__.py
shapeandshare/darkness/client/commands/worlds/get.py
shapeandshare/darkness/sdk/__init__.py
shapeandshare/darkness/sdk/common/__init__.py
shapeandshare/darkness/sdk/common/utils.py
shapeandshare/darkness/sdk/common/config/__init__.py
shapeandshare/darkness/sdk/common/config/environment.py
shapeandshare/darkness/sdk/contracts/__init__.py
shapeandshare/darkness/sdk/contracts/dtos/__init__.py
shapeandshare/darkness/sdk/contracts/dtos/coordinate.py
shapeandshare.darkness-0.4.18.dist-info/LICENSE
shapeandshare.darkness-0.4.18.dist-info/METADATA
shapeandshare.darkness-0.4.18.dist-info/WHEEL
shapeandshare.darkness-0.4.18.dist-info/entry_points.txt
shapeandshare.darkness-0.4.18.dist-info/top_level.txt
shapeandshare.darkness-0.4.18.dist-info/RECORD
