Metadata-Version: 2.1
Name: shapeandshare.darkness
Version: 0.4.18
Summary: Darkness
Author-email: "Joshua C. Burt" <joshburt@shapeandshare.com>
License: MIT License
Project-URL: Homepage, https://github.com/shapeandshare/darkness
Project-URL: Issues, https://github.com/shapeandshare/darkness/issues
Classifier: Programming Language :: Python :: 3
Classifier: License :: OSI Approved :: MIT License
Classifier: Operating System :: OS Independent
Requires-Python: >=3.12
License-File: LICENSE
Requires-Dist: fastapi
Requires-Dist: fastapi-utils[all]
Requires-Dist: typing-inspect
Requires-Dist: pydantic
Requires-Dist: uvicorn
Requires-Dist: requests
Requires-Dist: click
Requires-Dist: pymongo
